melano/__init__.py
melano/cli.py
melano/diff.py
melano/utils.py
melano-0.1.0.dist-info/entry_points.txt
melano-0.1.0.dist-info/LICENSE.txt
melano-0.1.0.dist-info/WHEEL
melano-0.1.0.dist-info/METADATA
melano-0.1.0.dist-info/RECORD
