Metadata-Version: 2.1
Name: melano
Version: 0.1.0
Summary: JSON utility
Home-page: https://github.com/suganthsundar/melano
License: MIT
Keywords: json,diff,utils
Author: Suganthan Sundararaju
Author-email: suganthsundar@gmail.com
Requires-Python: >=3.9,<4.0
Classifier: License :: OSI Approved :: MIT License
Classifier: Programming Language :: Python :: 3
Classifier: Programming Language :: Python :: 3.9
Requires-Dist: click (>=7.1.2,<8.0.0)
Requires-Dist: rich (>=10.1.0,<11.0.0)
Project-URL: Repository, https://github.com/suganthsundar/melano
